Metadata-Version: 2.1
Name: nni-upload-test
Version: 0.7.1904290925
Summary: Neural Network Intelligence package
Home-page: https://github.com/Microsoft/nni
Author: Microsoft NNI team
Author-email: nni@microsoft.com
License: MIT
Platform: UNKNOWN
Classifier: Programming Language :: Python :: 3
Classifier: License :: OSI Approved :: MIT License
Classifier: Operating System :: Microsoft :: Windows
Requires-Python: >=3.5
Requires-Dist: schema
Requires-Dist: ruamel.yaml
Requires-Dist: psutil
Requires-Dist: requests
Requires-Dist: astor
Requires-Dist: PythonWebHDFS
Requires-Dist: hyperopt
Requires-Dist: json-tricks
Requires-Dist: numpy
Requires-Dist: scipy
Requires-Dist: coverage
Requires-Dist: colorama
